trotter/__init__.py
trotter/__main__.py
trotter/amalgam.py
trotter/combination.py
trotter/combinatoric.py
trotter/composition.py
trotter/compound.py
trotter/helpers.py
trotter/permutation.py
trotter/subset.py
trotter-1.1.0.dist-info/LICENCE
trotter-1.1.0.dist-info/METADATA
trotter-1.1.0.dist-info/WHEEL
trotter-1.1.0.dist-info/top_level.txt
trotter-1.1.0.dist-info/RECORD
