Metadata-Version: 2.1
Name: trotter
Version: 1.1.0
Summary: Pseudo-lists containing arrangements of item selection types that commonly arise in combinatorics, such as combinations, permutations and subsets.
Home-page: https://github.com/ram6ler/python-trotter
Author: Richard Ambler
Author-email: rambler@wya.top
License: MIT Licence
Keywords: combinations,permutations,combinatorics,amalgams,compositions,subsets,compounds
Platform: UNKNOWN
Classifier: Programming Language :: Python :: 3
Classifier: Intended Audience :: Education
Classifier: Intended Audience :: Developers
Classifier: License :: OSI Approved :: MIT License
Classifier: Operating System :: OS Independent
Classifier: Topic :: Scientific/Engineering :: Mathematics
Requires-Python: >=3.10
License-File: LICENCE
